{"track_id":"10557","filters":["salads","meatGrill","homeMade"],"image":"https://tenbis-static.azureedge.net/restaurant-default-card-image/CuzineType_defaultcuisine_01.jpg","address":"הפטיש, 9 תל אביב-יפו","location":[34.7718895,32.0514288],"name":"מרכז סנדויץ טוניסאי","city":"גבעתיים","priceAverage":31.12,"menu":[{"name":"טוניסאי בבאגט","description":"טונה, תפו\"א, ביצה קשה, סלט, לימון ורטבי הבית ","price":27,"vegan":false,"vegetarian":false,"image":"https://d25t2285lxl5rf.cloudfront.net/images/dishes/79ab1f51-906f-49cb-8476-34b118bc1c2d.jpg","notFood":false,"drinks":false},{"name":"שניצל בבאגט","description":"","price":35,"vegan":false,"vegetarian":false,"image":"https://d25t2285lxl5rf.cloudfront.net/images/dishes/22a4ce42-f0f5-4079-98ba-02c9f58282c0.jpg","notFood":false,"drinks":false},{"name":"שקשוקה שתי ביצים בבאגט","description":"","price":25,"vegan":false,"vegetarian":true,"image":"https://d25t2285lxl5rf.cloudfront.net/images/dishes/2f6ec0f9-388b-45c4-8d0d-14845ae70fa7.jpg","notFood":false,"drinks":false},{"name":"פרגית בבאגט","description":"מוגש עם סלטים ","price":40,"vegan":false,"vegetarian":false,"image":"https://d25t2285lxl5rf.cloudfront.net/images/dishes/1ed62f7c-a63a-467d-94fc-7537fa32225a.jpg","notFood":false,"drinks":false},{"name":"טוניסאי","description":"טונה, תפו\"א, ביצה קשה, סלט, לימון ורטבי הבית, מוגש עם באגט","price":38,"vegan":false,"vegetarian":false,"image":"https://d25t2285lxl5rf.cloudfront.net/images/dishes/afc91336-cb71-4e8d-b58c-622e25b7e887.jpg","notFood":false,"drinks":false},{"name":"שקשוקה שתי ביצים","description":"מוגש עם באגט ","price":40,"vegan":false,"vegetarian":true,"image":"https://d25t2285lxl5rf.cloudfront.net/images/dishes/654329b3-e054-4bcd-ab42-69cb5dedd402.jpg","notFood":false,"drinks":false},{"name":"חביתה שתי ביצים","description":"מוגש עם באגט ","price":38,"vegan":false,"vegetarian":true,"image":"https://d25t2285lxl5rf.cloudfront.net/images/dishes/a16108a2-6a30-4086-ab78-f53b6eff06d4.jpg","notFood":false,"drinks":false},{"name":"חביתת ירק שתי ביצים","description":"מוגש עם באגט ","price":32,"vegan":false,"vegetarian":true,"image":"https://d25t2285lxl5rf.cloudfront.net/images/dishes/128c65d3-05aa-4ff6-8fb9-f68c74746db2.jpg","notFood":false,"drinks":false},{"name":"שניצל","description":"מוגש עם באגט ","price":45,"vegan":false,"vegetarian":false,"image":"https://d25t2285lxl5rf.cloudfront.net/images/dishes/5e8efa4a-786d-428e-935f-b0e7df4bf902.jpg","notFood":false,"drinks":false},{"name":"חומוס שקשוקה","description":"","price":40,"vegan":true,"vegetarian":true,"image":"https://d25t2285lxl5rf.cloudfront.net/images/dishes/661c1f54-9db0-41ff-abcc-e7669fa6639b.jpg","notFood":false,"drinks":false},{"name":"חזה עוף","description":"מוגש עם סלטים ","price":45,"vegan":false,"vegetarian":false,"image":"https://d25t2285lxl5rf.cloudfront.net/images/dishes/a1521859-97ee-48d2-bbb4-aeb9223882ae.jpg","notFood":false,"drinks":false},{"name":"קבב","description":"מוגש עם סלטים ","price":50,"vegan":false,"vegetarian":false,"image":"https://d25t2285lxl5rf.cloudfront.net/images/dishes/63b29101-0b76-4d1d-8bf4-ddadf10a61b0.jpg","notFood":false,"drinks":false},{"name":"פרגיות","description":"מוגש עם סלטים ","price":50,"vegan":false,"vegetarian":false,"image":"https://d25t2285lxl5rf.cloudfront.net/images/dishes/66ef5bdd-2605-4551-aadd-ea9fd8d83b1b.jpg","notFood":false,"drinks":false},{"name":"חומוס נקניקיות מרגז","description":"מוגש עם סלטים ","price":50,"vegan":true,"vegetarian":true,"image":"https://d25t2285lxl5rf.cloudfront.net/images/dishes/07f40531-0f17-47b0-b628-2d0f733856fb.jpg","notFood":false,"drinks":false},{"name":"מרגז בחמגשית","description":"","price":50,"vegan":true,"vegetarian":true,"image":"","notFood":false,"drinks":false},{"name":"אנטריקוט","description":"סלטים לבחירה ובגט בצד","price":55,"vegan":false,"vegetarian":false,"image":"","notFood":false,"drinks":false},{"name":"מעורב צלחת","description":"","price":55,"vegan":true,"vegetarian":true,"image":"","notFood":false,"drinks":false},{"name":"שאוורמה צלחת","description":"","price":55,"vegan":true,"vegetarian":true,"image":"","notFood":false,"drinks":false},{"name":"מיקס צלחת לבחירה","description":"קבב פרגית, קבב מרגז, פרגית מרגז","price":50,"vegan":false,"vegetarian":false,"image":"","notFood":false,"drinks":false},{"name":"מיקס בשרים משולש צלחת","description":"קבב פרגית מרגז","price":57,"vegan":false,"vegetarian":false,"image":"","notFood":false,"drinks":false},{"name":"טוניסאי בבאגט","description":"טונה, תפו\"א, ביצה קשה, סלט, לימון ורטבי הבית ","price":27,"vegan":false,"vegetarian":false,"image":"https://d25t2285lxl5rf.cloudfront.net/images/dishes/79ab1f51-906f-49cb-8476-34b118bc1c2d.jpg","notFood":false,"drinks":false},{"name":"שקשוקה שתי ביצים בבאגט","description":"","price":25,"vegan":false,"vegetarian":true,"image":"https://d25t2285lxl5rf.cloudfront.net/images/dishes/2f6ec0f9-388b-45c4-8d0d-14845ae70fa7.jpg","notFood":false,"drinks":false},{"name":"חביתת שתי ביצים בבאגט","description":"","price":25,"vegan":false,"vegetarian":true,"image":"https://d25t2285lxl5rf.cloudfront.net/images/dishes/d5032501-7e5e-45db-8568-e4dd04b6da36.jpg","notFood":false,"drinks":false},{"name":"חביתת ירק שתי ביצים בבאגט","description":"","price":25,"vegan":false,"vegetarian":true,"image":"https://d25t2285lxl5rf.cloudfront.net/images/dishes/fa0ee11c-05ba-4a53-9ca7-b068c1c0862a.jpg","notFood":false,"drinks":false},{"name":"שניצל בבאגט","description":"","price":35,"vegan":false,"vegetarian":false,"image":"https://d25t2285lxl5rf.cloudfront.net/images/dishes/22a4ce42-f0f5-4079-98ba-02c9f58282c0.jpg","notFood":false,"drinks":false},{"name":"קבב בבאגט","description":"מוגש עם סלטים","price":40,"vegan":false,"vegetarian":false,"image":"https://d25t2285lxl5rf.cloudfront.net/images/dishes/889b3daa-e840-4356-a0d3-defd0098cb12.jpg","notFood":false,"drinks":false},{"name":"נקניקיות  בבאגט","description":"מוגש עם סלטים ","price":40,"vegan":true,"vegetarian":true,"image":"https://d25t2285lxl5rf.cloudfront.net/images/dishes/244e8a53-bacb-44e4-81e2-feeb64ac6623.jpg","notFood":false,"drinks":false},{"name":"חזה עוף בבאגט","description":"מוגש עם סלטים ","price":35,"vegan":false,"vegetarian":false,"image":"https://d25t2285lxl5rf.cloudfront.net/images/dishes/2acac6e4-a4eb-4eae-95fe-c77104d2900d.jpg","notFood":false,"drinks":false},{"name":"מיקס בשרים בבאגט","description":"מוגש עם סלטים ","price":44,"vegan":false,"vegetarian":false,"image":"https://d25t2285lxl5rf.cloudfront.net/images/dishes/9aa17dc4-68da-4d3e-83af-ba944a04aba0.jpg","notFood":false,"drinks":false},{"name":"פרגית בבאגט","description":"מוגש עם סלטים ","price":40,"vegan":false,"vegetarian":false,"image":"https://d25t2285lxl5rf.cloudfront.net/images/dishes/1ed62f7c-a63a-467d-94fc-7537fa32225a.jpg","notFood":false,"drinks":false},{"name":"שווארמה בבאגט","description":"","price":44,"vegan":false,"vegetarian":false,"image":"","notFood":false,"drinks":false},{"name":"מעורב בבאגט","description":"","price":44,"vegan":true,"vegetarian":true,"image":"","notFood":false,"drinks":false},{"name":"אנטריקוט בבאגט","description":"","price":44,"vegan":false,"vegetarian":false,"image":"","notFood":false,"drinks":false},{"name":"סלטים בבאגט","description":"","price":20,"vegan":true,"vegetarian":true,"image":"","notFood":false,"drinks":false},{"name":"שקשוקה מרגז בבאגט","description":"","price":44,"vegan":true,"vegetarian":true,"image":"","notFood":false,"drinks":false},{"name":"מים מינרלים","description":"","price":9,"vegan":true,"vegetarian":true,"image":"","notFood":false,"drinks":false},{"name":"סודה","description":"","price":9,"vegan":true,"vegetarian":true,"image":"","notFood":false,"drinks":true},{"name":"פחית קולה","description":"","price":9,"vegan":true,"vegetarian":true,"image":"","notFood":false,"drinks":true},{"name":"פחית דיאט קולה","description":"","price":9,"vegan":true,"vegetarian":true,"image":"","notFood":false,"drinks":true},{"name":"פחית קולה  זירו","description":"","price":9,"vegan":true,"vegetarian":true,"image":"","notFood":false,"drinks":true},{"name":"פחית ספרייט","description":"","price":9,"vegan":true,"vegetarian":true,"image":"","notFood":false,"drinks":true},{"name":"פחית דיאט ספרייט","description":"","price":9,"vegan":true,"vegetarian":true,"image":"","notFood":false,"drinks":true},{"name":"פחית פאנטה","description":"","price":9,"vegan":true,"vegetarian":true,"image":"","notFood":false,"drinks":false},{"name":"בקבוק קולה","description":"","price":10,"vegan":true,"vegetarian":true,"image":"","notFood":false,"drinks":true},{"name":"בקבוק דיאט קולה","description":"","price":10,"vegan":true,"vegetarian":true,"image":"","notFood":false,"drinks":true},{"name":"בקבוק קולה זירו","description":"","price":10,"vegan":true,"vegetarian":true,"image":"","notFood":false,"drinks":true},{"name":"בקבוק ספרייט","description":"","price":10,"vegan":true,"vegetarian":true,"image":"","notFood":false,"drinks":true},{"name":"בקבוק דיאט ספרייט","description":"","price":10,"vegan":true,"vegetarian":true,"image":"","notFood":false,"drinks":true},{"name":"בקבוק פאנטה","description":"","price":10,"vegan":true,"vegetarian":true,"image":"","notFood":false,"drinks":true},{"name":"ליטר וחצי","description":"קולה זירו פנטה ספרייט נסטי לבחירה","price":15,"vegan":true,"vegetarian":true,"image":"","notFood":false,"drinks":true}]}