{"track_id":"19250","filters":["pizza","salads","pasta"],"image":"https://tenbis-static.azureedge.net/restaurant-card-image/ResCard_19250_20191114164707.jpg","address":"אלנבי, 79 תל אביב-יפו","location":[34.7716155,32.0669706],"name":"פיצה אנד טורטיה","city":"תל אביב-יפו","priceAverage":28,"menu":[{"name":"מגש L","description":"","price":59,"vegan":true,"vegetarian":true,"image":"https://d25t2285lxl5rf.cloudfront.net/images/dishes/b9207d3e-36c3-4aa2-901c-75cfe22d424b.jpg","notFood":false,"drinks":false},{"name":"אלפרדו","description":"","price":35,"vegan":true,"vegetarian":true,"image":"https://d25t2285lxl5rf.cloudfront.net/images/dishes/bf35efda-ce45-432a-a44f-beb74b26fb07.jpg","notFood":false,"drinks":false},{"name":"מגש XL","description":"","price":75,"vegan":true,"vegetarian":true,"image":"https://d25t2285lxl5rf.cloudfront.net/images/dishes/50c577a0-2f22-43d9-9f7e-85b67b4f5e7f.jpg","notFood":false,"drinks":false},{"name":"מגש L","description":"","price":59,"vegan":true,"vegetarian":true,"image":"https://d25t2285lxl5rf.cloudfront.net/images/dishes/b9207d3e-36c3-4aa2-901c-75cfe22d424b.jpg","notFood":false,"drinks":false},{"name":"פיצה אישית","description":"","price":35,"vegan":false,"vegetarian":true,"image":"","notFood":false,"drinks":false},{"name":"טונה","description":"רוטב חלפיניו, טונה, ביצה קשה, עגבניה, מלפפון חמוץ","price":39,"vegan":false,"vegetarian":false,"image":"https://d25t2285lxl5rf.cloudfront.net/images/dishes/0ca1bb95-e8ef-44cf-9962-1fe0d1a1b5ef.jpg","notFood":false,"drinks":false},{"name":"גבינות","description":"שמנת, מוצרלה, בולגרית, עגבניה","price":39,"vegan":false,"vegetarian":true,"image":"","notFood":false,"drinks":false},{"name":"סביח","description":"טחינה, חציל, עגבניה, ביצה קשה","price":39,"vegan":false,"vegetarian":true,"image":"","notFood":false,"drinks":false},{"name":"גוואקמולי","description":"ממרח אבוקדו, ביצה קשה, עגבניה, בצל","price":39,"vegan":false,"vegetarian":true,"image":"","notFood":false,"drinks":false},{"name":"פומודורו","description":"רוטב עגבניות, שמן זית, בזיליקום, שום","price":35,"vegan":true,"vegetarian":true,"image":"https://d25t2285lxl5rf.cloudfront.net/images/dishes/6b244d44-3cc1-4b51-b966-f7fe0cc3c11f.jpg","notFood":false,"drinks":false},{"name":"אלפרדו","description":"","price":35,"vegan":true,"vegetarian":true,"image":"https://d25t2285lxl5rf.cloudfront.net/images/dishes/bf35efda-ce45-432a-a44f-beb74b26fb07.jpg","notFood":false,"drinks":false},{"name":"רוזה","description":"רוטב עגבניות + רוטב שמנת","price":35,"vegan":false,"vegetarian":true,"image":"https://d25t2285lxl5rf.cloudfront.net/images/dishes/b81c0dd8-9fd8-420e-b55f-9d14452310f6.jpg","notFood":false,"drinks":false},{"name":"קולה 1.5","description":"","price":15,"vegan":true,"vegetarian":true,"image":"","notFood":false,"drinks":true},{"name":"נסטי אפרסק 1.5 ליטר","description":"","price":15,"vegan":true,"vegetarian":true,"image":"","notFood":false,"drinks":true},{"name":"קולה זירו 1.5","description":"","price":15,"vegan":true,"vegetarian":true,"image":"","notFood":false,"drinks":true},{"name":"ספרייט 1.5","description":"","price":15,"vegan":true,"vegetarian":true,"image":"","notFood":false,"drinks":true},{"name":"קולה","description":"","price":9,"vegan":true,"vegetarian":true,"image":"","notFood":false,"drinks":true},{"name":"זירו","description":"","price":9,"vegan":true,"vegetarian":true,"image":"","notFood":false,"drinks":false},{"name":"ספרייט","description":"","price":9,"vegan":true,"vegetarian":true,"image":"","notFood":false,"drinks":true},{"name":"נסטי אפרסק","description":"","price":9,"vegan":true,"vegetarian":true,"image":"","notFood":false,"drinks":true},{"name":"פחית קולה","description":"","price":8,"vegan":true,"vegetarian":true,"image":"","notFood":false,"drinks":true},{"name":"פחית ספרייט","description":"","price":8,"vegan":true,"vegetarian":true,"image":"","notFood":false,"drinks":true},{"name":"פחית קולה זירו","description":"","price":8,"vegan":true,"vegetarian":true,"image":"","notFood":false,"drinks":true}]}