{"track_id":"26653","filters":["homeMade","meatGrill","veganFood"],"image":"https://tenbis-static.azureedge.net/restaurant-default-card-image/CuzineType_homemade_09.jpg","address":"בארות יצחק, 1 בארות יצחק","location":[34.910221,32.042025],"name":"קורינה ","city":"אור יהודה","priceAverage":49.6875,"menu":[{"name":"עיסקית קובה סלק בליווי 2 תוספות לבחירה סלט ורוטב","description":"כדורי סולת במילוי בקר ברוטב אדום מסלק.","price":50,"vegan":false,"vegetarian":false,"image":"https://d25t2285lxl5rf.cloudfront.net/images/dishes/561163fc-919d-4883-b430-b2f238cf5802.jpg","notFood":false,"drinks":false},{"name":"עיסקית סמבוסק חומוס - צמחוני","description":"","price":45,"vegan":true,"vegetarian":true,"image":"https://d25t2285lxl5rf.cloudfront.net/images/dishes/4d6abb6f-51f1-44dc-b038-ed7caaea9e6d.jpg","notFood":false,"drinks":false},{"name":"עיסקית קציצות ברוקולי וכרובית","description":"","price":45,"vegan":true,"vegetarian":true,"image":"","notFood":false,"drinks":false},{"name":"עיסקית שווארמה עגל בליווי 2 תוספות סלט ורוטב","description":"מוגש בליווי 2 מנות חמות לבחירה סלט ירוק ורוטב לבחירה","price":55,"vegan":false,"vegetarian":false,"image":"https://d25t2285lxl5rf.cloudfront.net/images/dishes/0af4fe07-535e-49b1-8705-80c90daac0e2.jpg","notFood":false,"drinks":false},{"name":"עיסקית כבד עוף בטאריאקי מוגש בליווי 2 תוספות לבחירה סלט ורוטב.","description":"","price":50,"vegan":false,"vegetarian":false,"image":"https://d25t2285lxl5rf.cloudfront.net/images/dishes/b6ace163-b0db-4bbc-afdc-e3e9440ee295.jpg","notFood":false,"drinks":false},{"name":"עיסקית מפרום בליווי 2 תוספות סלט ורוטב","description":"2 יח' של מפרום","price":50,"vegan":true,"vegetarian":true,"image":"https://d25t2285lxl5rf.cloudfront.net/images/dishes/91cb775b-3cf2-4d1b-a54f-2da52d413a26.jpg","notFood":false,"drinks":false},{"name":"עיסקית מוסקה בליווי 2 תוספות לבחירה סלט ורוטב.","description":"2 יח' של מוסקה","price":50,"vegan":true,"vegetarian":true,"image":"https://d25t2285lxl5rf.cloudfront.net/images/dishes/1b1b5456-1b4b-48fe-b68a-3a8ecae5db21.jpg","notFood":false,"drinks":false},{"name":"עיסקית כרע עוף בליווי 2 תוספות לבחירה סלט ורוטב.","description":"","price":50,"vegan":false,"vegetarian":false,"image":"https://d25t2285lxl5rf.cloudfront.net/images/dishes/3ee9f8ef-3b5a-43fa-995e-945e8b1c072c.jpg","notFood":false,"drinks":false},{"name":"עיסקית קובה סלק בליווי 2 תוספות לבחירה סלט ורוטב","description":"כדורי סולת במילוי בקר ברוטב אדום מסלק.","price":50,"vegan":false,"vegetarian":false,"image":"https://d25t2285lxl5rf.cloudfront.net/images/dishes/561163fc-919d-4883-b430-b2f238cf5802.jpg","notFood":false,"drinks":false},{"name":"עיסקית קובה חמוסטה בליווי 2 תוספות סלט ורוטב.","description":"כדורי סולת במילוי בקר ברוטב צהוב חמצמץ","price":50,"vegan":false,"vegetarian":false,"image":"https://d25t2285lxl5rf.cloudfront.net/images/dishes/761ddc6a-0bc4-4d19-98f7-777594ead05f.jpg","notFood":false,"drinks":false},{"name":"עיסקית קציצות בקר בליווי 2 תוספות סלט ורוטב.","description":"","price":50,"vegan":false,"vegetarian":false,"image":"https://d25t2285lxl5rf.cloudfront.net/images/dishes/03e576f1-9054-4a30-a09a-92e1cbb580e6.jpg","notFood":false,"drinks":false},{"name":"עיסקית פלפל ממולא בליווי 2 תוספות לבחירה סלט ורוטב","description":"2 יח' של פלפל.","price":50,"vegan":true,"vegetarian":true,"image":"https://d25t2285lxl5rf.cloudfront.net/images/dishes/552d470b-2e61-4a5f-89f8-9ff5c9576382.jpg","notFood":false,"drinks":false},{"name":"עיסקית גולש בקר בליווי 2 תוספות לבחירה סלט ורוטב.","description":"קוביות בקר בבישול ארוך עם בצל גזר ותפו\"א.\n","price":50,"vegan":false,"vegetarian":false,"image":"","notFood":false,"drinks":false},{"name":"עיסקית מעורב בליווי 2 תוספות סלט ורוטב.","description":"הודו טחול ולבבות עשוי בפלאנצה עם בצל מטוגן.","price":50,"vegan":true,"vegetarian":true,"image":"","notFood":false,"drinks":false},{"name":"כריך אנטריקוט","description":"מוגש בגבטה לבנה עם רוטב שום חסה עגבניה מלפפון חמוץ ובצל מטוגן מוגש עם ציפס","price":50,"vegan":false,"vegetarian":false,"image":"https://d25t2285lxl5rf.cloudfront.net/images/dishes/ec6d3cb6-cfb3-48dc-a066-77df175f8e37.jpg","notFood":false,"drinks":false},{"name":"כריך סלופי גו","description":"בשר בקר טחון עם בצל מטוגן ורוטב ברביקיו מוגש בגבטה לבנה עם חסה עגבניה מלפפון ורוטב שום מוגש עם ציפס","price":50,"vegan":false,"vegetarian":false,"image":"https://d25t2285lxl5rf.cloudfront.net/images/dishes/ff63aea1-c9bd-4b59-926f-9f58156a40c5.jpg","notFood":false,"drinks":false}]}